setup.py
loadwave/__init__.py
loadwave.egg-info/PKG-INFO
loadwave.egg-info/SOURCES.txt
loadwave.egg-info/dependency_links.txt
loadwave.egg-info/requires.txt
loadwave.egg-info/top_level.txt