Metadata-Version: 2.1
Name: loadwave
Version: 0.4.3
Summary: Loader Animation
Author: r4isy
Author-email: r4isy@kenucorp.com
